[{"nationality":{"name":"United Kingdom"},"name":{"full":"NIAZ MOHAMMED CHOUDHURY","first":"NIAZ","last":"CHOUDHURY","father":"MOHAMMED","grand":""},"nameArabic":{"first":"","last":"","father":"","grand":""},"gender":"Male","dob":{"dmy":"01/12/1974"},"passIssueDt":{"dmy":"15/04/2014"},"passExpireDt":{"dmy":"15/08/2024"},"birthPlace":"DHAKA","profession":"Manager","passportNumber":"521560678","placeOfIssue":"IPS","codeline":"P<GBRCHOUDHURY<<NIAZ<MOHAMED<<<<<<<<<<<<<<<<5215606786GBR7412017M2408150<<<<<<<<<<<<<<04"}]